lain_cli/__init__.py
lain_cli/appversion.py
lain_cli/attach.py
lain_cli/auth.py
lain_cli/backup.py
lain_cli/build.py
lain_cli/clear.py
lain_cli/config.py
lain_cli/dashboard.py
lain_cli/deploy.py
lain_cli/enter.py
lain_cli/imagecheck.py
lain_cli/lain.py
lain_cli/login.py
lain_cli/logout.py
lain_cli/maintainer.py
lain_cli/meta.py
lain_cli/prepare.py
lain_cli/prepare_update.py
lain_cli/ps.py
lain_cli/push.py
lain_cli/reposit.py
lain_cli/rmi.py
lain_cli/run.py
lain_cli/scale.py
lain_cli/secret.py
lain_cli/sync.py
lain_cli/tag.py
lain_cli/test.py
lain_cli/undeploy.py
lain_cli/update.py
lain_cli/utils.py
lain_cli/validate.py
lain_cli/version.py
lain_cli-2.3.9.dist-info/DESCRIPTION.rst
lain_cli-2.3.9.dist-info/METADATA
lain_cli-2.3.9.dist-info/RECORD
lain_cli-2.3.9.dist-info/WHEEL
lain_cli-2.3.9.dist-info/entry_points.txt
lain_cli-2.3.9.dist-info/metadata.json
lain_cli-2.3.9.dist-info/top_level.txt
tests/__init__.py
tests/test_lain_cli.py
