Metadata-Version: 2.0
Name: lain-cli
Version: 2.3.9
Summary: UNKNOWN
Home-page: UNKNOWN
Author: UNKNOWN
Author-email: UNKNOWN
License: UNKNOWN
Platform: UNKNOWN
Requires-Dist: PyYAML (==3.11)
Requires-Dist: argh (==0.26.1)
Requires-Dist: entryclient (==2.3.0)
Requires-Dist: humanfriendly (==1.29)
Requires-Dist: lain-sdk (>=2.3.9)
Requires-Dist: pytest
Requires-Dist: requests (>=2.6.1)
Requires-Dist: tabulate (==0.7.5)
